{
  "dataset_revision": "e8379541af4e31359cca9fbcf4b00f2671dba205",
  "evaluation_time": 26.181763887405396,
  "kg_co2_emissions": null,
  "mteb_version": "1.14.20",
  "scores": {
    "test": [
      {
        "accuracy": 0.7311094452773613,
        "ap": 0.20973794848590618,
        "ap_weighted": 0.20973794848590618,
        "f1": 0.5987228722069342,
        "f1_weighted": 0.7808128917367644,
        "hf_subset": "en-ext",
        "languages": [
          "eng-Latn"
        ],
        "main_score": 0.7311094452773613,
        "scores_per_experiment": [
          {
            "accuracy": 0.7533733133433284,
            "ap": 0.22786648737031867,
            "ap_weighted": 0.22786648737031867,
            "f1": 0.619641642292276,
            "f1_weighted": 0.7981759591442499
          },
          {
            "accuracy": 0.7128935532233883,
            "ap": 0.2020063425311199,
            "ap_weighted": 0.2020063425311199,
            "f1": 0.5857730646527786,
            "f1_weighted": 0.7674229102963022
          },
          {
            "accuracy": 0.7511244377811095,
            "ap": 0.214279400687599,
            "ap_weighted": 0.214279400687599,
            "f1": 0.6113503855887732,
            "f1_weighted": 0.7958521344826571
          },
          {
            "accuracy": 0.7473763118440779,
            "ap": 0.21590665775453324,
            "ap_weighted": 0.21590665775453324,
            "f1": 0.6103928068464954,
            "f1_weighted": 0.7932683836827118
          },
          {
            "accuracy": 0.7001499250374813,
            "ap": 0.18870155314545095,
            "ap_weighted": 0.18870155314545095,
            "f1": 0.5719749473792288,
            "f1_weighted": 0.7573897095807556
          },
          {
            "accuracy": 0.7376311844077961,
            "ap": 0.21975751210877134,
            "ap_weighted": 0.21975751210877134,
            "f1": 0.6075586770802164,
            "f1_weighted": 0.7864083746556384
          },
          {
            "accuracy": 0.6896551724137931,
            "ap": 0.19242748754060096,
            "ap_weighted": 0.19242748754060096,
            "f1": 0.5689115773698015,
            "f1_weighted": 0.7495138951693131
          },
          {
            "accuracy": 0.7556221889055472,
            "ap": 0.23981312657224924,
            "ap_weighted": 0.23981312657224924,
            "f1": 0.6266769679800842,
            "f1_weighted": 0.8003582859613203
          },
          {
            "accuracy": 0.6821589205397302,
            "ap": 0.1890519468283044,
            "ap_weighted": 0.1890519468283044,
            "f1": 0.5632781012091357,
            "f1_weighted": 0.7436489995038307
          },
          {
            "accuracy": 0.7811094452773614,
            "ap": 0.20756897032011423,
            "ap_weighted": 0.20756897032011423,
            "f1": 0.6216705516705516,
            "f1_weighted": 0.8160902648908648
          }
        ]
      },
      {
        "accuracy": 0.7338805970149254,
        "ap": 0.3598628138586865,
        "ap_weighted": 0.3598628138586865,
        "f1": 0.6730894999849584,
        "f1_weighted": 0.7585225467416336,
        "hf_subset": "en",
        "languages": [
          "eng-Latn"
        ],
        "main_score": 0.7338805970149254,
        "scores_per_experiment": [
          {
            "accuracy": 0.6671641791044776,
            "ap": 0.30769289597188165,
            "ap_weighted": 0.30769289597188165,
            "f1": 0.6148144710756371,
            "f1_weighted": 0.7012868632852197
          },
          {
            "accuracy": 0.7701492537313432,
            "ap": 0.40000899737462475,
            "ap_weighted": 0.40000899737462475,
            "f1": 0.7095680958385877,
            "f1_weighted": 0.7903429730289285
          },
          {
            "accuracy": 0.7522388059701492,
            "ap": 0.368863313742854,
            "ap_weighted": 0.368863313742854,
            "f1": 0.6869370383714646,
            "f1_weighted": 0.7740060618363774
          },
          {
            "accuracy": 0.691044776119403,
            "ap": 0.30871222235074847,
            "ap_weighted": 0.30871222235074847,
            "f1": 0.6273487187341303,
            "f1_weighted": 0.7211681823196583
          },
          {
            "accuracy": 0.7567164179104477,
            "ap": 0.3798083589041466,
            "ap_weighted": 0.3798083589041466,
            "f1": 0.6941675931345231,
            "f1_weighted": 0.7783917532288375
          },
          {
            "accuracy": 0.7761194029850746,
            "ap": 0.37877934846341743,
            "ap_weighted": 0.37877934846341743,
            "f1": 0.7020845190665908,
            "f1_weighted": 0.7925223413382716
          },
          {
            "accuracy": 0.7492537313432835,
            "ap": 0.377298040100169,
            "ap_weighted": 0.377298040100169,
            "f1": 0.6894588152202701,
            "f1_weighted": 0.7724395151460847
          },
          {
            "accuracy": 0.7567164179104477,
            "ap": 0.3798083589041466,
            "ap_weighted": 0.3798083589041466,
            "f1": 0.6941675931345231,
            "f1_weighted": 0.7783917532288375
          },
          {
            "accuracy": 0.6925373134328359,
            "ap": 0.35278602828951006,
            "ap_weighted": 0.35278602828951006,
            "f1": 0.6489862768435724,
            "f1_weighted": 0.724277899421621
          },
          {
            "accuracy": 0.7268656716417911,
            "ap": 0.34487057448536684,
            "ap_weighted": 0.34487057448536684,
            "f1": 0.663361878430285,
            "f1_weighted": 0.7523981245824997
          }
        ]
      }
    ]
  },
  "task_name": "AmazonCounterfactualClassification"
}