{
  "dataset_revision": "59042f120c80e8afa9cdbb224f67076cec0fc9a7",
  "evaluation_time": 120.8539502620697,
  "kg_co2_emissions": null,
  "mteb_version": "1.14.20",
  "scores": {
    "test": [
      {
        "hf_subset": "default",
        "languages": [
          "eng-Latn"
        ],
        "main_score": 0.26296231898529415,
        "map": 0.26296231898529415,
        "mrr": 0.266551537067692,
        "nAUC_map_diff1": 0.18564203515158692,
        "nAUC_map_max": -0.26365003375255136,
        "nAUC_map_std": -0.08218183297647655,
        "nAUC_mrr_diff1": 0.16775528047095054,
        "nAUC_mrr_max": -0.20639388990480184,
        "nAUC_mrr_std": -0.07065114901858273
      }
    ]
  },
  "task_name": "MindSmallReranking"
}