{
  "dataset_revision": "1399c76144fd37290681b995c656ef9b2e06e26d",
  "evaluation_time": 91.1230571269989,
  "kg_co2_emissions": null,
  "mteb_version": "1.14.19",
  "scores": {
    "test": [
      {
        "accuracy": 0.35022,
        "f1": 0.3507158233909573,
        "f1_weighted": 0.3507158233909573,
        "hf_subset": "en",
        "languages": [
          "eng-Latn"
        ],
        "main_score": 0.35022,
        "scores_per_experiment": [
          {
            "accuracy": 0.3718,
            "f1": 0.372166939524063,
            "f1_weighted": 0.37216693952406293
          },
          {
            "accuracy": 0.3638,
            "f1": 0.36820332607168793,
            "f1_weighted": 0.36820332607168804
          },
          {
            "accuracy": 0.3376,
            "f1": 0.33926703678383063,
            "f1_weighted": 0.33926703678383063
          },
          {
            "accuracy": 0.3538,
            "f1": 0.3594829290852193,
            "f1_weighted": 0.3594829290852193
          },
          {
            "accuracy": 0.3702,
            "f1": 0.3613334659174144,
            "f1_weighted": 0.3613334659174144
          },
          {
            "accuracy": 0.3176,
            "f1": 0.3104274210942784,
            "f1_weighted": 0.3104274210942784
          },
          {
            "accuracy": 0.3272,
            "f1": 0.32836990424598145,
            "f1_weighted": 0.32836990424598145
          },
          {
            "accuracy": 0.3516,
            "f1": 0.35234442584812414,
            "f1_weighted": 0.3523444258481241
          },
          {
            "accuracy": 0.365,
            "f1": 0.366629607777938,
            "f1_weighted": 0.36662960777793807
          },
          {
            "accuracy": 0.3436,
            "f1": 0.3489331775610356,
            "f1_weighted": 0.3489331775610356
          }
        ]
      }
    ],
    "validation": [
      {
        "accuracy": 0.34819999999999995,
        "f1": 0.34875200923907,
        "f1_weighted": 0.34875200923907,
        "hf_subset": "en",
        "languages": [
          "eng-Latn"
        ],
        "main_score": 0.34819999999999995,
        "scores_per_experiment": [
          {
            "accuracy": 0.3552,
            "f1": 0.35901257582884155,
            "f1_weighted": 0.35901257582884155
          },
          {
            "accuracy": 0.358,
            "f1": 0.36248960617903164,
            "f1_weighted": 0.3624896061790317
          },
          {
            "accuracy": 0.342,
            "f1": 0.3444805257098171,
            "f1_weighted": 0.3444805257098171
          },
          {
            "accuracy": 0.3498,
            "f1": 0.3552909494139832,
            "f1_weighted": 0.35529094941398315
          },
          {
            "accuracy": 0.365,
            "f1": 0.3539427293988684,
            "f1_weighted": 0.3539427293988684
          },
          {
            "accuracy": 0.3196,
            "f1": 0.31346006716121233,
            "f1_weighted": 0.3134600671612123
          },
          {
            "accuracy": 0.335,
            "f1": 0.33505307836698706,
            "f1_weighted": 0.3350530783669871
          },
          {
            "accuracy": 0.3324,
            "f1": 0.3338507378081374,
            "f1_weighted": 0.3338507378081374
          },
          {
            "accuracy": 0.3792,
            "f1": 0.3807761797082495,
            "f1_weighted": 0.3807761797082495
          },
          {
            "accuracy": 0.3458,
            "f1": 0.3491636428155716,
            "f1_weighted": 0.3491636428155716
          }
        ]
      }
    ]
  },
  "task_name": "AmazonReviewsClassification"
}