{
  "dataset_revision": "6125ec4e24fa026cec8a478383ee943acfbd5449",
  "evaluation_time": 70.47950768470764,
  "kg_co2_emissions": null,
  "mteb_version": "1.14.20",
  "scores": {
    "test": [
      {
        "hf_subset": "default",
        "languages": [
          "eng-Latn"
        ],
        "main_score": 0.15258419244777313,
        "v_measure": 0.15258419244777313,
        "v_measure_std": 0.016338582582855112,
        "v_measures": [
          0.1932993849574567,
          0.15845979367299365,
          0.14030701552032082,
          0.15284718382320703,
          0.16142674755509806,
          0.16087822050025322,
          0.14133158197436724,
          0.1395801369176026,
          0.13701118008926588,
          0.14070067946716622
        ]
      }
    ]
  },
  "task_name": "TwentyNewsgroupsClustering"
}