{
  "dataset_revision": "d604517c81ca91fe16a244d1248fc021f9ecee7a",
  "evaluation_time": 18.78775978088379,
  "kg_co2_emissions": null,
  "mteb_version": "1.14.20",
  "scores": {
    "test": [
      {
        "accuracy": 0.5415676287492925,
        "f1": 0.5435611821151538,
        "f1_weighted": 0.5385494977779275,
        "hf_subset": "default",
        "languages": [
          "eng-Latn"
        ],
        "main_score": 0.5415676287492925,
        "scores_per_experiment": [
          {
            "accuracy": 0.5353706847764572,
            "f1": 0.5331288937911016,
            "f1_weighted": 0.5241230145287492
          },
          {
            "accuracy": 0.5503678551216752,
            "f1": 0.5534515073274281,
            "f1_weighted": 0.5495202847111845
          },
          {
            "accuracy": 0.5636672325976231,
            "f1": 0.5678560741678708,
            "f1_weighted": 0.5636781183092298
          },
          {
            "accuracy": 0.5780984719864176,
            "f1": 0.5817818855870635,
            "f1_weighted": 0.5783441421913548
          },
          {
            "accuracy": 0.5376344086021505,
            "f1": 0.5401235527521168,
            "f1_weighted": 0.5355531611819424
          },
          {
            "accuracy": 0.5376344086021505,
            "f1": 0.5391789477707669,
            "f1_weighted": 0.5309549164567039
          },
          {
            "accuracy": 0.5466893039049237,
            "f1": 0.5467510038008312,
            "f1_weighted": 0.5407188553277665
          },
          {
            "accuracy": 0.55631013016412,
            "f1": 0.5557858332276927,
            "f1_weighted": 0.5543630440850171
          },
          {
            "accuracy": 0.5110356536502547,
            "f1": 0.5149392008189316,
            "f1_weighted": 0.5090306146519714
          },
          {
            "accuracy": 0.49886813808715336,
            "f1": 0.502614921907735,
            "f1_weighted": 0.49920882633535535
          }
        ]
      }
    ]
  },
  "task_name": "TweetSentimentExtractionClassification"
}