{
  "dataset_revision": "ae752c7c21bf194d8b67fd573edf7ae58183cbe3",
  "evaluation_time": 15.92899489402771,
  "kg_co2_emissions": null,
  "mteb_version": "1.14.19",
  "scores": {
    "test": [
      {
        "cosine_pearson": 0.6157569253457835,
        "cosine_spearman": 0.6278689067113479,
        "euclidean_pearson": 0.6123685288976104,
        "euclidean_spearman": 0.6199547337596221,
        "hf_subset": "default",
        "languages": [
          "eng-Latn"
        ],
        "main_score": 0.6278689067113479,
        "manhattan_pearson": 0.6127790628770259,
        "manhattan_spearman": 0.62050068439223,
        "pearson": 0.6157569253457835,
        "spearman": 0.6278689067113479
      }
    ]
  },
  "task_name": "STS15"
}