{
  "dataset_revision": "fad2c6e8459f9e1c45d9315f4953d921437d70f8",
  "evaluation_time": 48.33050799369812,
  "kg_co2_emissions": null,
  "mteb_version": "1.14.20",
  "scores": {
    "test": [
      {
        "accuracy": 0.5544720914593141,
        "f1": 0.5344696198473103,
        "f1_weighted": 0.555889778439157,
        "hf_subset": "en",
        "languages": [
          "eng-Latn"
        ],
        "main_score": 0.5544720914593141,
        "scores_per_experiment": [
          {
            "accuracy": 0.5628782784129119,
            "f1": 0.5517155095177448,
            "f1_weighted": 0.5671825357730422
          },
          {
            "accuracy": 0.574310692669805,
            "f1": 0.5537123881570811,
            "f1_weighted": 0.5750426768492296
          },
          {
            "accuracy": 0.5622057834566241,
            "f1": 0.5436590679163076,
            "f1_weighted": 0.5665045535331978
          },
          {
            "accuracy": 0.5517821116341628,
            "f1": 0.5256370587213859,
            "f1_weighted": 0.5555465864766668
          },
          {
            "accuracy": 0.5638870208473437,
            "f1": 0.5422831881649516,
            "f1_weighted": 0.5608164918814639
          },
          {
            "accuracy": 0.5221923335574983,
            "f1": 0.4990538733244853,
            "f1_weighted": 0.5222045179316432
          },
          {
            "accuracy": 0.5443846671149967,
            "f1": 0.529146707457151,
            "f1_weighted": 0.5449687259556499
          },
          {
            "accuracy": 0.5521183591123067,
            "f1": 0.532620511022856,
            "f1_weighted": 0.5539637199258172
          },
          {
            "accuracy": 0.5716207128446537,
            "f1": 0.5459006756805258,
            "f1_weighted": 0.569212773858054
          },
          {
            "accuracy": 0.539340954942838,
            "f1": 0.5209672185106142,
            "f1_weighted": 0.5434552022068037
          }
        ]
      }
    ]
  },
  "task_name": "MassiveScenarioClassification"
}