{
  "dataset_revision": "d604517c81ca91fe16a244d1248fc021f9ecee7a",
  "evaluation_time": 20.003787994384766,
  "kg_co2_emissions": null,
  "mteb_version": "1.14.20",
  "scores": {
    "test": [
      {
        "accuracy": 0.4269383135257499,
        "f1": 0.4257658885074739,
        "f1_weighted": 0.42654175220269686,
        "hf_subset": "default",
        "languages": [
          "eng-Latn"
        ],
        "main_score": 0.4269383135257499,
        "scores_per_experiment": [
          {
            "accuracy": 0.4411431805319751,
            "f1": 0.4381357719617798,
            "f1_weighted": 0.43863104892037413
          },
          {
            "accuracy": 0.40492359932088284,
            "f1": 0.40582220772577166,
            "f1_weighted": 0.4045444411242878
          },
          {
            "accuracy": 0.4405772495755518,
            "f1": 0.4408169268413613,
            "f1_weighted": 0.4402669553728436
          },
          {
            "accuracy": 0.4524617996604414,
            "f1": 0.4509805423844133,
            "f1_weighted": 0.45272623631709497
          },
          {
            "accuracy": 0.4057724957555178,
            "f1": 0.40454122915384594,
            "f1_weighted": 0.4067665874030815
          },
          {
            "accuracy": 0.43208828522920206,
            "f1": 0.4328969985583308,
            "f1_weighted": 0.4325246726163513
          },
          {
            "accuracy": 0.4425580079230334,
            "f1": 0.43935235134732037,
            "f1_weighted": 0.44347784392536266
          },
          {
            "accuracy": 0.41992076966610076,
            "f1": 0.4183572309630892,
            "f1_weighted": 0.4201413813071049
          },
          {
            "accuracy": 0.4003961516694963,
            "f1": 0.4009946991018786,
            "f1_weighted": 0.39574091936315925
          },
          {
            "accuracy": 0.4295415959252971,
            "f1": 0.4257609270369478,
            "f1_weighted": 0.4305974356773081
          }
        ]
      }
    ]
  },
  "task_name": "TweetSentimentExtractionClassification"
}