{
  "dataset_revision": "1399c76144fd37290681b995c656ef9b2e06e26d",
  "evaluation_time": 20.245097160339355,
  "kg_co2_emissions": null,
  "mteb_version": "1.14.20",
  "scores": {
    "test": [
      {
        "accuracy": 0.32744,
        "f1": 0.325818402476297,
        "f1_weighted": 0.325818402476297,
        "hf_subset": "en",
        "languages": [
          "eng-Latn"
        ],
        "main_score": 0.32744,
        "scores_per_experiment": [
          {
            "accuracy": 0.3502,
            "f1": 0.34426944354567846,
            "f1_weighted": 0.3442694435456784
          },
          {
            "accuracy": 0.3294,
            "f1": 0.3337688445533812,
            "f1_weighted": 0.33376884455338124
          },
          {
            "accuracy": 0.3032,
            "f1": 0.30382657829270443,
            "f1_weighted": 0.30382657829270443
          },
          {
            "accuracy": 0.3146,
            "f1": 0.31061678014319305,
            "f1_weighted": 0.3106167801431931
          },
          {
            "accuracy": 0.3764,
            "f1": 0.37125191214098757,
            "f1_weighted": 0.37125191214098757
          },
          {
            "accuracy": 0.3,
            "f1": 0.2988535220901837,
            "f1_weighted": 0.2988535220901837
          },
          {
            "accuracy": 0.2782,
            "f1": 0.2802830384856464,
            "f1_weighted": 0.28028303848564645
          },
          {
            "accuracy": 0.3478,
            "f1": 0.34471078997259946,
            "f1_weighted": 0.34471078997259946
          },
          {
            "accuracy": 0.3306,
            "f1": 0.327665069929706,
            "f1_weighted": 0.327665069929706
          },
          {
            "accuracy": 0.344,
            "f1": 0.3429380456088901,
            "f1_weighted": 0.3429380456088901
          }
        ]
      }
    ]
  },
  "task_name": "AmazonReviewsClassification"
}