{
  "dataset_revision": "6031580fec1f6af667f0bd2da0a551cf4f0b2375",
  "evaluation_time": 13.244489908218384,
  "kg_co2_emissions": null,
  "mteb_version": "1.14.20",
  "scores": {
    "test": [
      {
        "cosine_pearson": 0.389592661359712,
        "cosine_spearman": 0.3734854811589407,
        "euclidean_pearson": 0.38653071534512035,
        "euclidean_spearman": 0.36961423015096384,
        "hf_subset": "default",
        "languages": [
          "eng-Latn"
        ],
        "main_score": 0.3734854811589407,
        "manhattan_pearson": 0.3860036965599353,
        "manhattan_spearman": 0.36892735792316406,
        "pearson": 0.389592661359712,
        "spearman": 0.3734854811589407
      }
    ]
  },
  "task_name": "STS14"
}